preprocessor.py
ocr_enhancer-0.1.0.dist-info/METADATA
ocr_enhancer-0.1.0.dist-info/WHEEL
ocr_enhancer-0.1.0.dist-info/top_level.txt
ocr_enhancer-0.1.0.dist-info/RECORD
