Metadata-Version: 2.2
Name: ocr-enhancer
Version: 0.1.0
Summary: Add your description here
Requires-Python: >=3.13
Requires-Dist: opencv-python>=4.11.0.86
